setup.py
expressions/__init__.py
expressions/compat.py
expressions/compiler.py
expressions/grammar.py
expressions.egg-info/PKG-INFO
expressions.egg-info/SOURCES.txt
expressions.egg-info/dependency_links.txt
expressions.egg-info/requires.txt
expressions.egg-info/top_level.txt