Metadata-Version: 1.1
Name: expressions
Version: 0.2.3
Summary: Extensible arithmetic expression parser and compiler
Home-page: http://databrewery.org
Author: Stefan Urbanek
Author-email: stefan.urbanek@gmail.com
License: MIT license
Keywords: arithmetic expression
Platform: UNKNOWN
Classifier: Development Status :: 5 - Production/Stable
Classifier: Intended Audience :: Developers
Classifier: Intended Audience :: Science/Research
Classifier: License :: OSI Approved :: MIT License
Classifier: Programming Language :: Python :: 3
Classifier: Topic :: Scientific/Engineering
Classifier: Topic :: Utilities
